<annotation>
  <folder>Tes_Model/images</folder>
  <filename>0001063.jpg</filename>
  <segmented>0</segmented>
  <size>
    <width>720</width>
    <height>405</height>
    <depth>3</depth>
  </size>
  <object>
    <name>wheel</name>
    <pose>Unspecified</pose>
    <truncated>0</truncated>
    <difficult>0</difficult>
    <bndbox>
      <xmin>304</xmin>
      <ymin>163</ymin>
      <xmax>461</xmax>
      <ymax>363</ymax>
    </bndbox>
  </object>
  <object>
    <name>wheel</name>
    <pose>Unspecified</pose>
    <truncated>0</truncated>
    <difficult>0</difficult>
    <bndbox>
      <xmin>56</xmin>
      <ymin>192</ymin>
      <xmax>119</xmax>
      <ymax>294</ymax>
    </bndbox>
  </object>
</annotation>
