<annotation>
  <folder>Tes_Model/images</folder>
  <filename>0001145.jpg</filename>
  <segmented>0</segmented>
  <size>
    <width>423</width>
    <height>336</height>
    <depth>3</depth>
  </size>
  <object>
    <name>wheel</name>
    <pose>Unspecified</pose>
    <truncated>0</truncated>
    <difficult>0</difficult>
    <bndbox>
      <xmin>174</xmin>
      <ymin>211</ymin>
      <xmax>260</xmax>
      <ymax>335</ymax>
    </bndbox>
  </object>
  <object>
    <name>wheel</name>
    <pose>Unspecified</pose>
    <truncated>0</truncated>
    <difficult>0</difficult>
    <bndbox>
      <xmin>359</xmin>
      <ymin>153</ymin>
      <xmax>405</xmax>
      <ymax>235</ymax>
    </bndbox>
  </object>
</annotation>
