<annotation>
  <folder>Tes_Model/images</folder>
  <filename>0001108.jpg</filename>
  <segmented>0</segmented>
  <size>
    <width>827</width>
    <height>510</height>
    <depth>3</depth>
  </size>
  <object>
    <name>wheel</name>
    <pose>Unspecified</pose>
    <truncated>0</truncated>
    <difficult>0</difficult>
    <bndbox>
      <xmin>511</xmin>
      <ymin>228</ymin>
      <xmax>546</xmax>
      <ymax>313</ymax>
    </bndbox>
  </object>
  <object>
    <name>wheel</name>
    <pose>Unspecified</pose>
    <truncated>0</truncated>
    <difficult>0</difficult>
    <bndbox>
      <xmin>608</xmin>
      <ymin>233</ymin>
      <xmax>633</xmax>
      <ymax>302</ymax>
    </bndbox>
  </object>
</annotation>
