<annotation>
  <folder>Tes_Model/images</folder>
  <filename>0001061.jpg</filename>
  <segmented>0</segmented>
  <size>
    <width>1199</width>
    <height>412</height>
    <depth>3</depth>
  </size>
  <object>
    <name>wheel</name>
    <pose>Unspecified</pose>
    <truncated>0</truncated>
    <difficult>0</difficult>
    <bndbox>
      <xmin>557</xmin>
      <ymin>197</ymin>
      <xmax>695</xmax>
      <ymax>397</ymax>
    </bndbox>
  </object>
  <object>
    <name>wheel</name>
    <pose>Unspecified</pose>
    <truncated>0</truncated>
    <difficult>0</difficult>
    <bndbox>
      <xmin>845</xmin>
      <ymin>185</ymin>
      <xmax>906</xmax>
      <ymax>303</ymax>
    </bndbox>
  </object>
</annotation>
