<annotation>
  <folder>Tes_Model/images</folder>
  <filename>001516.jpg</filename>
  <segmented>0</segmented>
  <size>
    <width>1920</width>
    <height>1080</height>
    <depth>3</depth>
  </size>
  <object>
    <name>wheel</name>
    <pose>Unspecified</pose>
    <truncated>0</truncated>
    <difficult>0</difficult>
    <bndbox>
      <xmin>831</xmin>
      <ymin>836</ymin>
      <xmax>1067</xmax>
      <ymax>1076</ymax>
    </bndbox>
  </object>
  <object>
    <name>wheel</name>
    <pose>Unspecified</pose>
    <truncated>0</truncated>
    <difficult>0</difficult>
    <bndbox>
      <xmin>1532</xmin>
      <ymin>561</ymin>
      <xmax>1710</xmax>
      <ymax>816</ymax>
    </bndbox>
  </object>
</annotation>
