<annotation>
  <folder>Tes_Model/images</folder>
  <filename>001847.jpg</filename>
  <segmented>0</segmented>
  <size>
    <width>1920</width>
    <height>1080</height>
    <depth>3</depth>
  </size>
  <object>
    <name>wheel</name>
    <pose>Unspecified</pose>
    <truncated>0</truncated>
    <difficult>0</difficult>
    <bndbox>
      <xmin>808</xmin>
      <ymin>805</ymin>
      <xmax>1036</xmax>
      <ymax>1072</ymax>
    </bndbox>
  </object>
  <object>
    <name>wheel</name>
    <pose>Unspecified</pose>
    <truncated>0</truncated>
    <difficult>0</difficult>
    <bndbox>
      <xmin>1710</xmin>
      <ymin>437</ymin>
      <xmax>1888</xmax>
      <ymax>735</ymax>
    </bndbox>
  </object>
</annotation>
