<annotation>
  <folder>Tes_Model/images</folder>
  <filename>003849.jpg</filename>
  <segmented>0</segmented>
  <size>
    <width>400</width>
    <height>266</height>
    <depth>3</depth>
  </size>
  <object>
    <name>wheel</name>
    <pose>Unspecified</pose>
    <truncated>0</truncated>
    <difficult>0</difficult>
    <bndbox>
      <xmin>41</xmin>
      <ymin>132</ymin>
      <xmax>105</xmax>
      <ymax>194</ymax>
    </bndbox>
  </object>
  <object>
    <name>wheel</name>
    <pose>Unspecified</pose>
    <truncated>0</truncated>
    <difficult>0</difficult>
    <bndbox>
      <xmin>289</xmin>
      <ymin>132</ymin>
      <xmax>351</xmax>
      <ymax>192</ymax>
    </bndbox>
  </object>
</annotation>
