<annotation>
  <folder>Tes_Model/images</folder>
  <filename>003894.jpg</filename>
  <segmented>0</segmented>
  <size>
    <width>424</width>
    <height>360</height>
    <depth>3</depth>
  </size>
  <object>
    <name>wheel</name>
    <pose>Unspecified</pose>
    <truncated>0</truncated>
    <difficult>0</difficult>
    <bndbox>
      <xmin>125</xmin>
      <ymin>204</ymin>
      <xmax>196</xmax>
      <ymax>320</ymax>
    </bndbox>
  </object>
  <object>
    <name>wheel</name>
    <pose>Unspecified</pose>
    <truncated>0</truncated>
    <difficult>0</difficult>
    <bndbox>
      <xmin>45</xmin>
      <ymin>147</ymin>
      <xmax>70</xmax>
      <ymax>213</ymax>
    </bndbox>
  </object>
</annotation>
