<annotation>
  <folder>Tes_Model/images</folder>
  <filename>004061.jpg</filename>
  <segmented>0</segmented>
  <size>
    <width>1024</width>
    <height>683</height>
    <depth>3</depth>
  </size>
  <object>
    <name>wheel</name>
    <pose>Unspecified</pose>
    <truncated>0</truncated>
    <difficult>0</difficult>
    <bndbox>
      <xmin>395</xmin>
      <ymin>391</ymin>
      <xmax>534</xmax>
      <ymax>598</ymax>
    </bndbox>
  </object>
  <object>
    <name>wheel</name>
    <pose>Unspecified</pose>
    <truncated>0</truncated>
    <difficult>0</difficult>
    <bndbox>
      <xmin>146</xmin>
      <ymin>385</ymin>
      <xmax>307</xmax>
      <ymax>556</ymax>
    </bndbox>
  </object>
  <object>
    <name>wheel</name>
    <pose>Unspecified</pose>
    <truncated>0</truncated>
    <difficult>0</difficult>
    <bndbox>
      <xmin>744</xmin>
      <ymin>480</ymin>
      <xmax>868</xmax>
      <ymax>616</ymax>
    </bndbox>
  </object>
</annotation>
