<annotation>
  <folder>Tes_Model/images</folder>
  <filename>004342.jpg</filename>
  <segmented>0</segmented>
  <size>
    <width>800</width>
    <height>600</height>
    <depth>3</depth>
  </size>
  <object>
    <name>wheel</name>
    <pose>Unspecified</pose>
    <truncated>0</truncated>
    <difficult>0</difficult>
    <bndbox>
      <xmin>383</xmin>
      <ymin>344</ymin>
      <xmax>542</xmax>
      <ymax>501</ymax>
    </bndbox>
  </object>
  <object>
    <name>wheel</name>
    <pose>Unspecified</pose>
    <truncated>0</truncated>
    <difficult>0</difficult>
    <bndbox>
      <xmin>52</xmin>
      <ymin>289</ymin>
      <xmax>131</xmax>
      <ymax>393</ymax>
    </bndbox>
  </object>
</annotation>
