<annotation>
  <folder>Tes_Model/images</folder>
  <filename>004438.jpg</filename>
  <segmented>0</segmented>
  <size>
    <width>434</width>
    <height>326</height>
    <depth>3</depth>
  </size>
  <object>
    <name>wheel</name>
    <pose>Unspecified</pose>
    <truncated>0</truncated>
    <difficult>0</difficult>
    <bndbox>
      <xmin>155</xmin>
      <ymin>183</ymin>
      <xmax>223</xmax>
      <ymax>274</ymax>
    </bndbox>
  </object>
  <object>
    <name>wheel</name>
    <pose>Unspecified</pose>
    <truncated>0</truncated>
    <difficult>0</difficult>
    <bndbox>
      <xmin>48</xmin>
      <ymin>168</ymin>
      <xmax>85</xmax>
      <ymax>229</ymax>
    </bndbox>
  </object>
</annotation>
