<annotation>
  <folder>Tes_Model/images</folder>
  <filename>004893.jpg</filename>
  <segmented>0</segmented>
  <size>
    <width>300</width>
    <height>225</height>
    <depth>3</depth>
  </size>
  <object>
    <name>wheel</name>
    <pose>Unspecified</pose>
    <truncated>0</truncated>
    <difficult>0</difficult>
    <bndbox>
      <xmin>35</xmin>
      <ymin>166</ymin>
      <xmax>71</xmax>
      <ymax>210</ymax>
    </bndbox>
  </object>
  <object>
    <name>wheel</name>
    <pose>Unspecified</pose>
    <truncated>0</truncated>
    <difficult>0</difficult>
    <bndbox>
      <xmin>209</xmin>
      <ymin>172</ymin>
      <xmax>255</xmax>
      <ymax>215</ymax>
    </bndbox>
  </object>
</annotation>
