<annotation>
  <folder>Tes_Model/images</folder>
  <filename>005079.jpg</filename>
  <segmented>0</segmented>
  <size>
    <width>640</width>
    <height>480</height>
    <depth>3</depth>
  </size>
  <object>
    <name>wheel</name>
    <pose>Unspecified</pose>
    <truncated>0</truncated>
    <difficult>0</difficult>
    <bndbox>
      <xmin>311</xmin>
      <ymin>203</ymin>
      <xmax>454</xmax>
      <ymax>371</ymax>
    </bndbox>
  </object>
  <object>
    <name>wheel</name>
    <pose>Unspecified</pose>
    <truncated>0</truncated>
    <difficult>0</difficult>
    <bndbox>
      <xmin>589</xmin>
      <ymin>187</ymin>
      <xmax>631</xmax>
      <ymax>274</ymax>
    </bndbox>
  </object>
</annotation>
