<annotation>
  <folder>Tes_Model/images</folder>
  <filename>005657.jpg</filename>
  <segmented>0</segmented>
  <size>
    <width>1024</width>
    <height>768</height>
    <depth>3</depth>
  </size>
  <object>
    <name>wheel</name>
    <pose>Unspecified</pose>
    <truncated>0</truncated>
    <difficult>0</difficult>
    <bndbox>
      <xmin>399</xmin>
      <ymin>417</ymin>
      <xmax>505</xmax>
      <ymax>590</ymax>
    </bndbox>
  </object>
  <object>
    <name>wheel</name>
    <pose>Unspecified</pose>
    <truncated>0</truncated>
    <difficult>0</difficult>
    <bndbox>
      <xmin>116</xmin>
      <ymin>272</ymin>
      <xmax>210</xmax>
      <ymax>434</ymax>
    </bndbox>
  </object>
</annotation>
