<annotation>
  <folder>Tes_Model/images</folder>
  <filename>005999.jpg</filename>
  <segmented>0</segmented>
  <size>
    <width>2048</width>
    <height>1536</height>
    <depth>3</depth>
  </size>
  <object>
    <name>wheel</name>
    <pose>Unspecified</pose>
    <truncated>0</truncated>
    <difficult>0</difficult>
    <bndbox>
      <xmin>1085</xmin>
      <ymin>670</ymin>
      <xmax>1314</xmax>
      <ymax>977</ymax>
    </bndbox>
  </object>
  <object>
    <name>wheel</name>
    <pose>Unspecified</pose>
    <truncated>0</truncated>
    <difficult>0</difficult>
    <bndbox>
      <xmin>1713</xmin>
      <ymin>682</ymin>
      <xmax>1879</xmax>
      <ymax>973</ymax>
    </bndbox>
  </object>
</annotation>
