<annotation>
  <folder>Tes_Model/images</folder>
  <filename>005939.jpg</filename>
  <segmented>0</segmented>
  <size>
    <width>800</width>
    <height>600</height>
    <depth>3</depth>
  </size>
  <object>
    <name>wheel</name>
    <pose>Unspecified</pose>
    <truncated>0</truncated>
    <difficult>0</difficult>
    <bndbox>
      <xmin>279</xmin>
      <ymin>319</ymin>
      <xmax>430</xmax>
      <ymax>475</ymax>
    </bndbox>
  </object>
  <object>
    <name>wheel</name>
    <pose>Unspecified</pose>
    <truncated>0</truncated>
    <difficult>0</difficult>
    <bndbox>
      <xmin>641</xmin>
      <ymin>255</ymin>
      <xmax>709</xmax>
      <ymax>355</ymax>
    </bndbox>
  </object>
</annotation>
