<annotation>
  <folder>Tes_Model/images</folder>
  <filename>007700.jpg</filename>
  <segmented>0</segmented>
  <size>
    <width>1599</width>
    <height>1032</height>
    <depth>3</depth>
  </size>
  <object>
    <name>wheel</name>
    <pose>Unspecified</pose>
    <truncated>0</truncated>
    <difficult>0</difficult>
    <bndbox>
      <xmin>1092</xmin>
      <ymin>559</ymin>
      <xmax>1237</xmax>
      <ymax>949</ymax>
    </bndbox>
  </object>
  <object>
    <name>wheel</name>
    <pose>Unspecified</pose>
    <truncated>0</truncated>
    <difficult>0</difficult>
    <bndbox>
      <xmin>1466</xmin>
      <ymin>356</ymin>
      <xmax>1534</xmax>
      <ymax>572</ymax>
    </bndbox>
  </object>
</annotation>
