<annotation>
  <folder>Tes_Model/images</folder>
  <filename>008029.jpg</filename>
  <segmented>0</segmented>
  <size>
    <width>527</width>
    <height>317</height>
    <depth>3</depth>
  </size>
  <object>
    <name>wheel</name>
    <pose>Unspecified</pose>
    <truncated>0</truncated>
    <difficult>0</difficult>
    <bndbox>
      <xmin>333</xmin>
      <ymin>189</ymin>
      <xmax>386</xmax>
      <ymax>270</ymax>
    </bndbox>
  </object>
  <object>
    <name>wheel</name>
    <pose>Unspecified</pose>
    <truncated>0</truncated>
    <difficult>0</difficult>
    <bndbox>
      <xmin>413</xmin>
      <ymin>177</ymin>
      <xmax>441</xmax>
      <ymax>255</ymax>
    </bndbox>
  </object>
</annotation>
