<annotation>
  <folder>Tes_Model/images</folder>
  <filename>008157.jpg</filename>
  <segmented>0</segmented>
  <size>
    <width>358</width>
    <height>269</height>
    <depth>3</depth>
  </size>
  <object>
    <name>wheel</name>
    <pose>Unspecified</pose>
    <truncated>0</truncated>
    <difficult>0</difficult>
    <bndbox>
      <xmin>133</xmin>
      <ymin>181</ymin>
      <xmax>185</xmax>
      <ymax>250</ymax>
    </bndbox>
  </object>
  <object>
    <name>wheel</name>
    <pose>Unspecified</pose>
    <truncated>0</truncated>
    <difficult>0</difficult>
    <bndbox>
      <xmin>27</xmin>
      <ymin>171</ymin>
      <xmax>70</xmax>
      <ymax>235</ymax>
    </bndbox>
  </object>
</annotation>
