<annotation>
  <folder>Tes_Model/images</folder>
  <filename>008366.jpg</filename>
  <segmented>0</segmented>
  <size>
    <width>450</width>
    <height>294</height>
    <depth>3</depth>
  </size>
  <object>
    <name>wheel</name>
    <pose>Unspecified</pose>
    <truncated>0</truncated>
    <difficult>0</difficult>
    <bndbox>
      <xmin>258</xmin>
      <ymin>182</ymin>
      <xmax>326</xmax>
      <ymax>270</ymax>
    </bndbox>
  </object>
  <object>
    <name>wheel</name>
    <pose>Unspecified</pose>
    <truncated>0</truncated>
    <difficult>0</difficult>
    <bndbox>
      <xmin>362</xmin>
      <ymin>151</ymin>
      <xmax>394</xmax>
      <ymax>228</ymax>
    </bndbox>
  </object>
</annotation>
