<annotation>
  <folder>Tes_Model/images</folder>
  <filename>008597.jpg</filename>
  <segmented>0</segmented>
  <size>
    <width>500</width>
    <height>375</height>
    <depth>3</depth>
  </size>
  <object>
    <name>wheel</name>
    <pose>Unspecified</pose>
    <truncated>0</truncated>
    <difficult>0</difficult>
    <bndbox>
      <xmin>143</xmin>
      <ymin>194</ymin>
      <xmax>219</xmax>
      <ymax>302</ymax>
    </bndbox>
  </object>
  <object>
    <name>wheel</name>
    <pose>Unspecified</pose>
    <truncated>0</truncated>
    <difficult>0</difficult>
    <bndbox>
      <xmin>18</xmin>
      <ymin>174</ymin>
      <xmax>51</xmax>
      <ymax>241</ymax>
    </bndbox>
  </object>
</annotation>
