<annotation>
  <folder>Tes_Model/images</folder>
  <filename>008916.jpg</filename>
  <segmented>0</segmented>
  <size>
    <width>275</width>
    <height>183</height>
    <depth>3</depth>
  </size>
  <object>
    <name>wheel</name>
    <pose>Unspecified</pose>
    <truncated>0</truncated>
    <difficult>0</difficult>
    <bndbox>
      <xmin>72</xmin>
      <ymin>107</ymin>
      <xmax>106</xmax>
      <ymax>177</ymax>
    </bndbox>
  </object>
  <object>
    <name>wheel</name>
    <pose>Unspecified</pose>
    <truncated>0</truncated>
    <difficult>0</difficult>
    <bndbox>
      <xmin>13</xmin>
      <ymin>74</ymin>
      <xmax>27</xmax>
      <ymax>114</ymax>
    </bndbox>
  </object>
</annotation>
